media_fetching/__init__.py
media_fetching/exceptions.py
media_fetching/media_fetching_service.py
media_fetching/telemetry.py
media_fetching/enrichers/__init__.py
media_fetching/enrichers/dbm.py
media_fetching/enrichers/enricher.py
media_fetching/enrichers/extra_info.py
media_fetching/enrichers/googleads.py
media_fetching/enrichers/tagging.py
media_fetching/enrichers/youtube.py
media_fetching/entrypoints/__init__.py
media_fetching/entrypoints/cli.py
media_fetching/entrypoints/server.py
media_fetching/entrypoints/tracer.py
media_fetching/sources/__init__.py
media_fetching/sources/dbm.py
media_fetching/sources/fake.py
media_fetching/sources/fetcher.py
media_fetching/sources/file.py
media_fetching/sources/googleads.py
media_fetching/sources/models.py
media_fetching/sources/queries.py
media_fetching/sources/sql.py
media_fetching/sources/youtube.py
media_fetching-0.6.0.dist-info/METADATA
media_fetching-0.6.0.dist-info/WHEEL
media_fetching-0.6.0.dist-info/entry_points.txt
media_fetching-0.6.0.dist-info/top_level.txt
media_fetching-0.6.0.dist-info/RECORD
