Metadata-Version: 2.4
Name: media-fetching
Version: 0.6.0
Summary: Simplified fetching of media for Filonov library
Author-email: Andrei Markin <amarkin@google.com>, Sergei Dorogin <segy@google.com>, "Google Inc. (gTech gPS CSE team)" <no-reply@google.com>
Classifier: Development Status :: 4 - Beta
Classifier: Programming Language :: Python
Requires-Python: >=3.10
Requires-Dist: media-tagging>=2.2
Requires-Dist: garf-youtube>=1.0.0
Requires-Dist: garf-bid-manager>=1.0.0
Requires-Dist: garf-google-ads>=1.0.0
Requires-Dist: garf-executors[bq,sql]>=1.0.0
Requires-Dist: garf_core>=1.0.0
Requires-Dist: typer
Requires-Dist: opentelemetry-api
Requires-Dist: opentelemetry-sdk
Requires-Dist: opentelemetry-exporter-otlp
Provides-Extra: server
Requires-Dist: media-tagging[server]; extra == "server"
Requires-Dist: media-similarity[server]; extra == "server"
Provides-Extra: all
Requires-Dist: media-fetching[server]; extra == "all"
